{
  "entityName": "RacecarBlue",
  "image": "racecar_blue.png",
  "health": 1,
  "xPos": 100,
  "yPos": 100,
  "xVel": 10,
  "yVel": 10,
  "fixed": false,
  "permeable": false,
  "maxXVel": 500,
  "maxYVel": 500,

  "height": 25,
  "width": 89,
  "scheme": "ControllerBindings",
  "actionBundles": [
    {
      "ID": "LEFT_THUMBSTICK_RIGHT",
      "Control": [
        {
          "action": "AccelerateX",
          "param": "300.0"
        },
        {
          "action": "SetXDirection",
          "param": "forwards"
        }
      ]
    },
    {
      "ID": "LEFT_THUMBSTICK_LEFT",
      "Control": [
        {
          "action": "AccelerateX",
          "param": "-300.0"
        },
        {
          "action": "SetXDirection",
          "param": "backwards"
        }
      ]
    },
    {
      "ID": "W",
      "Control": [
        {
          "action": "AccelerateY",
          "param": "-300.0"
        }
      ]
    },
    {
      "ID": "S",
      "Control": [
        {
          "action": "AccelerateY",
          "param": "+300.0"
        }
      ]
    },
    {
      "ID": "A_BUTTON",
      "Control": [
        {
          "action": "Jump",
          "param": "-750.0"
        }
      ]
    }
  ],
  "collisionBundles": [
    {
      "ID": "rivalracer.Rock",
      "Control": [
        {
          "action": "SetBoundedLeft",
          "param": "true",
          "orientation": "E"
        },
        {
          "action": "SetBoundedRight",
          "param": "true",
          "orientation": "W"

        },
        {
          "action": "SetBoundedBottom",
          "param": "true",
          "orientation": "N"
        },
        {
          "action": "SetBoundedTop",
          "param": "true",
          "orientation": "S"
        }
      ]
    },
    {
      "ID": "rivalracer.Cobblestone",
      "Control": [
        {
          "action": "SetBoundedLeft",
          "param": "true",
          "orientation": "E"
        },
        {
          "action": "SetBoundedRight",
          "param": "true",
          "orientation": "W"

        },
        {
          "action": "SetBoundedBottom",
          "param": "true",
          "orientation": "N"
        },
        {
          "action": "SetBoundedTop",
          "param": "true",
          "orientation": "S"
        }
      ]
    },
    {
      "ID": "DEFAULT",
      "Control": [
        {
          "action": "NoAction",
          "param": "false",
          "orientation": "DEFAULT"
        }
      ]
    }
  ]
}